LICENSE
MANIFEST.in
README.rst
setup.py
splitipy/__init__.py
splitipy/__main__.py
splitipy/splitipy.py
splitipy/stuff.py
splitipy.egg-info/PKG-INFO
splitipy.egg-info/SOURCES.txt
splitipy.egg-info/dependency_links.txt
splitipy.egg-info/entry_points.txt
splitipy.egg-info/top_level.txt