Metadata-Version: 1.0
Name: splitipy
Version: 1.0.0
Summary: Python CLI application to split and join files for easy transfer via external media.
Home-page: https://github.com/lokeshthegenius/splitipy
Author: Lokesh Devnani
Author-email: contact@lokeshd.com
License: UNKNOWN
Platform: UNKNOWN
